any2-0.3.1.dist-info/DESCRIPTION.rst
any2-0.3.1.dist-info/top_level.txt
any2-0.3.1.dist-info/METADATA
any2-0.3.1.dist-info/RECORD
any2-0.3.1.dist-info/WHEEL
any2-0.3.1.dist-info/metadata.json
any2-0.3.1.dist-info/entry_points.txt
any2/main.py
any2/transformers.py
any2/__init__.py
any2/exceptions.py
any2/adapters.py
