Metadata-Version: 2.0
Name: any2
Version: 0.3.1
Summary: Base package for any2*
Home-page: https://bitbucket.org/faide/any2
Author: Florent Aide
Author-email: florent.aide@gmail.com
License: BSD
Platform: UNKNOWN
Requires-Dist: six
